imc_analysis/__init__.py
imc_analysis/logging.py
imc_analysis/main.py
imc_analysis/pl.py
imc_analysis/tl.py
imc_analysis/types.py
imc_analysis/utils.py
imc_analysis/tests/__init__.py
imc_analysis/tests/pl_test.py
imc_analysis/tests/tl_test.py
imc_analysis-2025.2.123.dist-info/METADATA
imc_analysis-2025.2.123.dist-info/WHEEL
imc_analysis-2025.2.123.dist-info/entry_points.txt
imc_analysis-2025.2.123.dist-info/top_level.txt
imc_analysis-2025.2.123.dist-info/RECORD
