Metadata-Version: 2.1
Name: imc-analysis
Version: 2025.2.123
Summary: A multi-file Python command line tool with commands qc, phenotype, and visualize.
Home-page: https://github.com/jkim810/imc-analysis
Author: Junbum Kim
Author-email: jkim0810@gmail.com
Requires-Python: >=3.8
Requires-Dist: click
Requires-Dist: pathlib
Requires-Dist: tifffile
Requires-Dist: tqdm
Requires-Dist: pandas
Requires-Dist: squidpy ==1.6.1
Requires-Dist: scanpy ==1.10.3
Requires-Dist: anndata ==0.9.1
Requires-Dist: scikit-image ==0.20.0
Requires-Dist: scipy ==1.9.1
Requires-Dist: seaborn
Requires-Dist: pyyaml ==6.0
Requires-Dist: pydot ==1.4.2
Requires-Dist: pingouin
